{
  "title": "Agent Mesh — Cost per Edge",
  "description": "One question: which agent edge is costing the conversation? USD is rounded to four decimal places.",
  "tags": ["agent-mesh-radar", "cost", "edge"], "version": "v5", "uploadedGrafana": false, "variables": {}, "panelMap": {},
  "layout": [{"i":"edge-kpi","x":0,"y":0,"w":12,"h":5},{"i":"edge-table","x":0,"y":5,"w":12,"h":7},{"i":"edge-red","x":0,"y":12,"w":12,"h":7}],
  "widgets": [
    {"id":"edge-kpi","title":"Total conversation edge cost (USD)","panelTypes":"value","timePreferance":"GLOBAL_TIME","yAxisUnit":"usd","thresholds":[{"value":0.01,"color":"yellow"},{"value":0.02,"color":"red"}],"query":{"queryType":"builder","builder":{"queryData":[{"queryName":"A","dataSource":"traces","expression":"A","stepInterval":10,"aggregations":[{"expression":"sum(agentmesh.cost.usd)"}],"filter":{"expression":"name = 'a2a.call' AND agentmesh.cost.usd EXISTS"},"groupBy":[],"legend":"conversation USD"}],"queryFormulas":[]}}},
    {"id":"edge-table","title":"Cost by source → destination","panelTypes":"table","timePreferance":"GLOBAL_TIME","yAxisUnit":"usd","columnUnits":{"A":"usd"},"thresholds":[{"value":0.01,"color":"yellow"},{"value":0.02,"color":"red"}],"query":{"queryType":"builder","builder":{"queryData":[{"queryName":"A","dataSource":"traces","expression":"A","stepInterval":10,"aggregations":[{"expression":"sum(agentmesh.cost.usd)"}],"filter":{"expression":"name = 'a2a.call' AND agentmesh.cost.usd EXISTS"},"groupBy":[{"key":"agentmesh.src","type":"tag"},{"key":"peer.service","type":"tag"}],"legend":"{{agentmesh.src}} → {{peer.service}}"}],"queryFormulas":[]}}},
    {"id":"edge-red","title":"Per-edge RED: P95 latency (ms) and request rate","panelTypes":"graph","timePreferance":"GLOBAL_TIME","yAxisUnit":"ms","columnUnits":{"A":"ms","B":"reqps"},"thresholds":[{"value":200,"color":"yellow"},{"value":500,"color":"red"}],"query":{"queryType":"builder","builder":{"queryData":[{"queryName":"A","dataSource":"metrics","expression":"A","stepInterval":10,"aggregations":[{"metricName":"signoz_latency_bucket","spaceAggregation":"p95","reduceTo":"avg"}],"filter":{"expression":"operation = 'a2a.call'"},"groupBy":[{"key":"service.name","type":"tag"}],"legend":"P95 ms {{service.name}}"},{"queryName":"B","dataSource":"metrics","expression":"B","stepInterval":10,"aggregations":[{"metricName":"signoz_calls_total","timeAggregation":"rate","spaceAggregation":"sum","reduceTo":"avg"}],"filter":{"expression":"operation = 'a2a.call'"},"groupBy":[{"key":"service.name","type":"tag"}],"legend":"requests/s {{service.name}}"}],"queryFormulas":[]}}}
  ]
}
